Metadata-Version: 1.1
Name: timeshade
Version: 21.0.1
Summary: Shade nighttime of time-series
Home-page: https://github.com/justinshenk/timeshade
Author: Justin Shenk
Author-email: shenkjustin@gmail.com
License: MIT
Keywords: plot,shade,nighttime,dark,time series
Platform: UNKNOWN
Classifier: Development Status :: 5 - Production/Stable
Classifier: License :: OSI Approved :: MIT License
Classifier: Natural Language :: English
Classifier: Programming Language :: Python
Classifier: Programming Language :: Python :: 3.6
